quart_babel/__init__.py
quart_babel/core.py
quart_babel/domain.py
quart_babel/formatters.py
quart_babel/locale.py
quart_babel/py.typed
quart_babel/speaklater.py
quart_babel/timezone.py
quart_babel/utils.py
quart_babel-1.0.7.dist-info/METADATA
quart_babel-1.0.7.dist-info/WHEEL
quart_babel-1.0.7.dist-info/RECORD
