Metadata-Version: 2.1
Name: quart_babel
Version: 1.0.7
Summary: Implements i18n and l10n support for Quart.
Home-page: https://github.com/Quart-Addons/quart-babel
License: MIT
Author: Chris Rood
Author-email: quart.addons@gmail.com
Requires-Python: >=3.8
Classifier: Development Status :: 4 - Beta
Classifier: Environment :: Web Environment
Classifier: Intended Audience :: Developers
Classifier: License :: OSI Approved :: MIT License
Classifier: Operating System :: OS Independent
Classifier: Programming Language :: Python
Classifier: Programming Language :: Python :: 3
Classifier: Programming Language :: Python :: 3.8
Classifier: Programming Language :: Python :: 3.9
Classifier: Programming Language :: Python :: 3.10
Classifier: Programming Language :: Python :: 3.11
Classifier: Programming Language :: Python :: 3.12
Classifier: Topic :: Internet :: WWW/HTTP :: Dynamic Content
Classifier: Topic :: Software Development :: Libraries :: Python Modules
Requires-Dist: Babel (>=2.11)
Requires-Dist: pytz (>=2023.3)
Requires-Dist: quart (>=0.19)
Requires-Dist: types-pytz (>=2024.1.0.20240417)
Project-URL: Documentation, https://quart-babel.readthedocs.io/en/latest/
Project-URL: Repository, https://github.com/Quart-Addons/quart-babel
